wordss/__init__.py
wordss/main1.py
wordss/main2.py
wordss/main3.py
wordss-0.1.5.dist-info/licenses/LICENSE.txt
wordss-0.1.5.dist-info/WHEEL
wordss-0.1.5.dist-info/METADATA
wordss-0.1.5.dist-info/RECORD
