Metadata-Version: 2.4
Name: wordss
Version: 0.1.5
Summary: A simple python package used to count letters,vowels,consonents of a word
Author-email: Vijayasarathi <vijayasarathi871@gmail.com>
Requires-Python: >=3.8
License-File: LICENSE.txt
